<?xml version="1.0" encoding="UTF-8" standalone="no"?>
<databaseChangeLog xmlns="http://www.liquibase.org/xml/ns/dbchangelog" xmlns:xsi="http://www.w3.org/2001/XMLSchema-instance"
                   xsi:schemaLocation="http://www.liquibase.org/xml/ns/dbchangelog http://www.liquibase.org/xml/ns/dbchangelog/dbchangelog-2.0.xsd">

    <changeSet author="vsds" id="bucketisation">
        <preConditions onFail="MARK_RAN">
            <not>
                <tableExists tableName="fragmentation_bucketisation"/>
            </not>
        </preConditions>
        <createTable tableName="fragmentation_bucketisation">
            <column autoIncrement="true" name="id" startWith="19711" type="BIGINT">
                <constraints nullable="false" primaryKey="true" primaryKeyName="fragmentation_bucketisation_pkey"/>
            </column>
            <column name="view_name" type="VARCHAR(255)"/>
            <column name="fragment_id" type="VARCHAR(255)"/>
            <column name="member_id" type="VARCHAR(255)"/>
            <column name="sequence_nr" type="BIGINT">
                <constraints nullable="false"/>
            </column>
        </createTable>
        <createIndex indexName="fragmentation_bucketisation_view_name" tableName="fragmentation_bucketisation">
            <column name="view_name"/>
        </createIndex>
        <createIndex indexName="fragmentation_bucketisation_fragment_id" tableName="fragmentation_bucketisation">
            <column name="fragment_id"/>
        </createIndex>
        <createIndex indexName="fragmentation_bucketisation_sequence_nr" tableName="fragmentation_bucketisation">
            <column name="sequence_nr"/>
        </createIndex>

    </changeSet>

</databaseChangeLog>